{
  "version": "2.6.0",
  "summary": {
    "title": "STRIDE",
    "owner": "",
    "description": "",
    "id": 0
  },
  "detail": {
    "contributors": [],
    "diagrams": [
      {
        "id": 0,
        "title": "Coffee Ordering Web App",
        "diagramType": "STRIDE",
        "placeholder": "New STRIDE diagram description",
        "thumbnail": "./public/content/images/thumbnail.stride.jpg",
        "version": "2.6.0",
        "cells": [
          {
            "position": {
              "x": 640,
              "y": 220
            },
            "size": {
              "width": 250,
              "height": 180
            },
            "attrs": {
              "text": {
                "text": "Web Application Server"
              },
              "body": {
                "stroke": "#333333",
                "strokeWidth": 1.5,
                "strokeDasharray": null
              }
            },
            "visible": true,
            "shape": "process",
            "ports": {
              "groups": {
                "top": {
                  "position": "top",
                  "attrs": {
                    "circle": {
                      "r": 4,
                      "magnet": true,
                      "stroke": "#5F95FF",
                      "strokeWidth": 1,
                      "fill": "#fff",
                      "style": {
                        "visibility": "hidden"
                      }
                    }
                  }
                },
                "right": {
                  "position": "right",
                  "attrs": {
                    "circle": {
                      "r": 4,
                      "magnet": true,
                      "stroke": "#5F95FF",
                      "strokeWidth": 1,
                      "fill": "#fff",
                      "style": {
                        "visibility": "hidden"
                      }
                    }
                  }
                },
                "bottom": {
                  "position": "bottom",
                  "attrs": {
                    "circle": {
                      "r": 4,
                      "magnet": true,
                      "stroke": "#5F95FF",
                      "strokeWidth": 1,
                      "fill": "#fff",
                      "style": {
                        "visibility": "hidden"
                      }
                    }
                  }
                },
                "left": {
                  "position": "left",
                  "attrs": {
                    "circle": {
                      "r": 4,
                      "magnet": true,
                      "stroke": "#5F95FF",
                      "strokeWidth": 1,
                      "fill": "#fff",
                      "style": {
                        "visibility": "hidden"
                      }
                    }
                  }
                }
              },
              "items": [
                {
                  "group": "top",
                  "id": "ac1169b2-8dbe-4aab-a02c-df37bb73954a"
                },
                {
                  "group": "right",
                  "id": "cab47bd5-368c-4a38-beec-60f85318ef6c"
                },
                {
                  "group": "bottom",
                  "id": "f9fac8f6-1025-45d7-b06d-f00099a8582c"
                },
                {
                  "group": "left",
                  "id": "8948d40b-5252-4564-8d97-1a2776d7fabb"
                }
              ]
            },
            "id": "fdecc813-0b85-406e-a3c3-9713ca6132db",
            "zIndex": 1,
            "data": {
              "type": "tm.Process",
              "name": "Web Application Server",
              "description": "Handles Authentication, Orders, Menu, Reports, Payments",
              "outOfScope": false,
              "isTrustBoundary": false,
              "reasonOutOfScope": "",
              "hasOpenThreats": false,
              "handlesCardPayment": false,
              "handlesGoodsOrServices": false,
              "isWebApplication": false,
              "privilegeLevel": "",
              "threats": []
            },
            "tools": {
              "items": [
                "boundary",
                "button-remove"
              ],
              "name": null
            }
          }
        ]
      }
    ],
    "diagramTop": 1,
    "reviewer": "",
    "threatTop": 1
  }
}